monodeal/__init__.py
monodeal/actions.py
monodeal/deck.py
monodeal/game.py
monodeal/py.typed
monodeal-0.0.2.dist-info/licenses/LICENSE
monodeal-0.0.2.dist-info/METADATA
monodeal-0.0.2.dist-info/WHEEL
monodeal-0.0.2.dist-info/top_level.txt
monodeal-0.0.2.dist-info/RECORD
