Metadata-Version: 2.4
Name: monodeal
Version: 0.0.2
Summary: Monopoly Deal simulator
Author-email: Chris Shucksmith <chris@shucksmith.co.uk>
Project-URL: Homepage, https://github.com/shuckc/monodeal
Project-URL: Issues, https://github.com/shuckc/monodeal/issues
Classifier: Programming Language :: Python :: 3.11
Classifier: Programming Language :: Python :: 3.12
Classifier: Programming Language :: Python :: 3.13
Classifier: License :: OSI Approved :: MIT License
Classifier: Operating System :: OS Independent
Requires-Python: >=3.11
License-File: LICENSE
Dynamic: license-file
